{
    "launch_mission_id": 5303,
    "launch_mission": "NROL-145",
    "launch_pad_id": 1,
    "launch_pad_name": "Vandenberg SFB",
    "launch_pad_country": "United States",
    "launch_desc": "A SpaceX Falcon 9 rocket will launch the\nNROL-145 mission on Sunday, April 20,\n2025 at 12:29 PM (UTC).",
    "launch_est_time": "2025-04-20T12:29Z",
    "launch_purpose": "B1082",
    "launch_quicktext": "Falcon 9 - NROL-145 - Sun Apr 20, 2025 10:27:00 UTC (L+00:30:25) - https://rocketlaunch.live/launch/nrol-145 for info/stream",
    "launch_last_update": "2025-04-20T10:50:23+00:00",
    "subject_title": "Rocket Launch Update"
}